liboextensioncreator/__init__.py
liboextensioncreator/liboextensioncreator.py
liboextensioncreator/license_files/cc-by-sa-4.0.txt
liboextensioncreator/license_files/gpl-2.0.txt
liboextensioncreator/license_files/gpl-3.0.txt
liboextensioncreator/license_files/lgpl-2.1.txt
liboextensioncreator/license_files/lgpl-3.0.txt
liboextensioncreator-0.2.1.dist-info/LICENSE
liboextensioncreator-0.2.1.dist-info/METADATA
liboextensioncreator-0.2.1.dist-info/WHEEL
liboextensioncreator-0.2.1.dist-info/top_level.txt
liboextensioncreator-0.2.1.dist-info/RECORD
