Metadata-Version: 2.1
Name: liboextensioncreator
Version: 0.2.1
Summary: A package to create LibreOffice non-code extensions
Home-page: https://github.com/andreasma/liboextensioncreator
Author: Andreas Mantke
Author-email: maand@gmx.de
License: LGPLv2+
Project-URL: Bug Tracker, https://github.com/andreasma/liboextensioncreator/issues
Platform: UNKNOWN
Classifier: Programming Language :: Python :: 3
Classifier: License :: OSI Approved :: GNU Lesser General Public License v2 or later (LGPLv2+)
Classifier: Operating System :: OS Independent
Requires-Python: >=3.6
Requires-Dist: PyQt5
Requires-Dist: validators
